swh/search/__init__.py
swh/search/cli.py
swh/search/elasticsearch.py
swh/search/exc.py
swh/search/in_memory.py
swh/search/interface.py
swh/search/journal_client.py
swh/search/metrics.py
swh/search/py.typed
swh/search/translator.py
swh/search/utils.py
swh/search/api/__init__.py
swh/search/api/client.py
swh/search/api/server.py
swh/search/query_language/.gitignore
swh/search/query_language/grammar.js
swh/search/query_language/sample_query
swh/search/query_language/tokens.js
swh/search/query_language/src/grammar.json
swh/search/query_language/src/node-types.json
swh/search/query_language/src/parser.c
swh/search/query_language/src/tree_sitter/parser.h
swh/search/query_language/test/corpus/combinations.txt
swh/search/static/swh_ql.so
swh/search/tests/__init__.py
swh/search/tests/conftest.py
swh/search/tests/test_api_client.py
swh/search/tests/test_cli.py
swh/search/tests/test_elasticsearch.py
swh/search/tests/test_in_memory.py
swh/search/tests/test_init.py
swh/search/tests/test_journal_client.py
swh/search/tests/test_search.py
swh/search/tests/test_server.py
swh/search/tests/test_translator.py
swh/search/tests/test_utils.py
swh_search-0.23.0.dist-info/licenses/AUTHORS
swh_search-0.23.0.dist-info/licenses/LICENSE
swh_search-0.23.0.dist-info/METADATA
swh_search-0.23.0.dist-info/WHEEL
swh_search-0.23.0.dist-info/entry_points.txt
swh_search-0.23.0.dist-info/top_level.txt
swh_search-0.23.0.dist-info/RECORD
