Metadata-Version: 2.4
Name: swh.search
Version: 0.23.0
Summary: Software Heritage search service
Author-email: Software Heritage developers <swh-devel@inria.fr>
Project-URL: Homepage, https://gitlab.softwareheritage.org/swh/devel/swh-search
Project-URL: Bug Reports, https://gitlab.softwareheritage.org/swh/devel/swh-search/-/issues
Project-URL: Funding, https://www.softwareheritage.org/donate
Project-URL: Documentation, https://docs.softwareheritage.org/devel/swh-search/
Project-URL: Source, https://gitlab.softwareheritage.org/swh/devel/swh-search.git
Classifier: Programming Language :: Python :: 3
Classifier: Intended Audience :: Developers
Classifier: License :: OSI Approved :: GNU General Public License v3 (GPLv3)
Classifier: Operating System :: OS Independent
Classifier: Development Status :: 3 - Alpha
Requires-Python: >=3.9
License-File: LICENSE
License-File: AUTHORS
Requires-Dist: click
Requires-Dist: elasticsearch<9.0.0,>=8.0.0
Requires-Dist: typing-extensions
Requires-Dist: tree_sitter<0.22.0
Requires-Dist: iso8601
Requires-Dist: swh.core[http]>=4.5.1
Requires-Dist: swh.indexer
Requires-Dist: swh.journal>=0.1.0
Requires-Dist: swh.model>=6.13.0
Provides-Extra: testing
Requires-Dist: click; extra == "testing"
Requires-Dist: elasticsearch<9.0.0,>=8.0.0; extra == "testing"
Requires-Dist: typing-extensions; extra == "testing"
Requires-Dist: tree_sitter<0.22.0; extra == "testing"
Requires-Dist: iso8601; extra == "testing"
Requires-Dist: swh.core[http]>=4.5.1; extra == "testing"
Requires-Dist: swh.indexer; extra == "testing"
Requires-Dist: swh.journal>=0.1.0; extra == "testing"
Requires-Dist: swh.model>=6.13.0; extra == "testing"
Requires-Dist: confluent-kafka; extra == "testing"
Requires-Dist: msgpack-types; extra == "testing"
Requires-Dist: pytest>=8.1; extra == "testing"
Requires-Dist: pytest-mock; extra == "testing"
Requires-Dist: swh.core[testing]; extra == "testing"
Requires-Dist: swh.journal[pytest]>=2.0.0; extra == "testing"
Requires-Dist: types-confluent-kafka; extra == "testing"
Requires-Dist: types-pytz; extra == "testing"
Requires-Dist: types-pyyaml; extra == "testing"
Requires-Dist: types-requests; extra == "testing"
Requires-Dist: types-setuptools; extra == "testing"
Dynamic: license-file
